pomice/__init__.py
pomice/enums.py
pomice/events.py
pomice/exceptions.py
pomice/filters.py
pomice/objects.py
pomice/player.py
pomice/pool.py
pomice/py.typed
pomice/queue.py
pomice/routeplanner.py
pomice/utils.py
pomice/applemusic/__init__.py
pomice/applemusic/client.py
pomice/applemusic/exceptions.py
pomice/applemusic/objects.py
pomice/spotify/__init__.py
pomice/spotify/client.py
pomice/spotify/exceptions.py
pomice/spotify/objects.py
pomice-2.10.0.dist-info/licenses/LICENSE
pomice-2.10.0.dist-info/METADATA
pomice-2.10.0.dist-info/WHEEL
pomice-2.10.0.dist-info/top_level.txt
pomice-2.10.0.dist-info/RECORD
