Metadata-Version: 2.4
Name: pomice
Version: 2.10.0
Summary: The modern Lavalink wrapper designed for Discord.py
Home-page: https://github.com/cloudwithax/pomice
Author: cloudwithax
License: GPL
Keywords: pomice,lavalink,discord.py
Classifier: Framework :: AsyncIO
Classifier: Operating System :: OS Independent
Classifier: Natural Language :: English
Classifier: Intended Audience :: Developers
Classifier: Programming Language :: Python :: 3 :: Only
Classifier: Programming Language :: Python :: 3.8
Classifier: Topic :: Software Development :: Libraries :: Python Modules
Classifier: Topic :: Software Development :: Libraries
Classifier: Topic :: Internet
Requires-Python: >=3.8
License-File: LICENSE
Requires-Dist: aiohttp<4,>=3.7.4
Requires-Dist: orjson
Requires-Dist: websockets
Dynamic: author
Dynamic: classifier
Dynamic: description
Dynamic: description-content-type
Dynamic: home-page
Dynamic: keywords
Dynamic: license
Dynamic: license-file
Dynamic: requires-dist
Dynamic: requires-python
Dynamic: summary
